cloudshell/__init__.py
cloudshell/f5/__init__.py
cloudshell/f5/autoload/__init__.py
cloudshell/f5/autoload/f5_generic_snmp_autoload.py
cloudshell/f5/autoload/snmp_if_table.py
cloudshell/f5/cli/__init__.py
cloudshell/f5/cli/f5_cli_configurator.py
cloudshell/f5/cli/f5_command_modes.py
cloudshell/f5/cli/f5_ssh_session.py
cloudshell/f5/cli/f5_telnet_session.py
cloudshell/f5/command_actions/__init__.py
cloudshell/f5/command_actions/enable_disable_snmp_actions.py
cloudshell/f5/command_actions/sys_config_actions.py
cloudshell/f5/command_templates/__init__.py
cloudshell/f5/command_templates/enable_disable_snmp.py
cloudshell/f5/command_templates/f5_config_templates.py
cloudshell/f5/flows/__init__.py
cloudshell/f5/flows/f5_autoload_flow.py
cloudshell/f5/flows/f5_configuration_flow.py
cloudshell/f5/flows/f5_enable_disable_snmp_flow.py
cloudshell/f5/flows/f5_firmware_flow.py
cloudshell/f5/flows/f5_state_flow.py
cloudshell/f5/snmp/__init__.py
cloudshell/f5/snmp/mibs/F5-BIGIP-COMMON-MIB.py
cloudshell/f5/snmp/mibs/F5-BIGIP-LOCAL-MIB.py
cloudshell/f5/snmp/mibs/F5-BIGIP-SYSTEM-MIB.py
cloudshell/f5/snmp/mibs/IANAifType-MIB.py
cloudshell/f5/snmp/mibs/INET-ADDRESS-MIB.py
cloudshell/f5/snmp/mibs/TRANSPORT-ADDRESS-MIB.py
cloudshell/f5/snmp/mibs/__init__.py
tests/__init__.py
tests/f5/__init__.py
tests/f5/test_placeholder.py
cloudshell_f5-2.0.4.dist-info/METADATA
cloudshell_f5-2.0.4.dist-info/WHEEL
cloudshell_f5-2.0.4.dist-info/top_level.txt
cloudshell_f5-2.0.4.dist-info/RECORD
